wan/__init__.py
wan/cli.py
wan/notify.py
wan/py.typed
wan/settings.py
wan/utils.py
wan/watch.py
wanot-0.0.3.dist-info/LICENSE
wanot-0.0.3.dist-info/METADATA
wanot-0.0.3.dist-info/WHEEL
wanot-0.0.3.dist-info/entry_points.txt
wanot-0.0.3.dist-info/top_level.txt
wanot-0.0.3.dist-info/RECORD
