Metadata-Version: 2.1
Name: wanot
Version: 0.0.3
Summary: Wait and notify conveniently
Author-email: Xiao Yang <afe.young@gmail.com>, zhupr <zplongr@hotmail.com>, gazh <v-gazh@hotmail.com>
License: MIT
Project-URL: documentation, https://you-n-g.github.io/wan
Project-URL: issue, https://github.com/you-n-g/wan/issues
Project-URL: repository, https://github.com/you-n-g/wan
Keywords: copier-template,full-development-lifecycle,project-template,serious-scaffold
Classifier: Development Status :: 4 - Beta
Classifier: License :: OSI Approved :: MIT License
Classifier: Operating System :: OS Independent
Classifier: Programming Language :: Python :: 3 :: Only
Classifier: Programming Language :: Python :: 3.8
Classifier: Programming Language :: Python :: 3.9
Classifier: Programming Language :: Python :: 3.10
Classifier: Programming Language :: Python :: 3.11
Classifier: Programming Language :: Python :: 3.12
Requires-Python: >=3.8
License-File: LICENSE
Requires-Dist: pydantic-settings
Requires-Dist: typer[all]
Requires-Dist: loguru
Requires-Dist: notifiers
Requires-Dist: fire
Requires-Dist: psutil
Requires-Dist: iterfzf
Requires-Dist: PyYAML
Requires-Dist: watchdog
